data/__init__.py
data/rasa_print.py
rasa_print-0.3.1.dist-info/LICENSE
rasa_print-0.3.1.dist-info/METADATA
rasa_print-0.3.1.dist-info/WHEEL
rasa_print-0.3.1.dist-info/top_level.txt
rasa_print-0.3.1.dist-info/RECORD
