Metadata-Version: 2.1
Name: rasa-print
Version: 0.3.1
Summary: Rasa NLU addons a natural language parser for bots
Home-page: https://rasa.com
Author: Zhong Lei
Author-email: 625015751@qq.com
Maintainer: Zhong Lei
Maintainer-email: 625015751@qq.com
License: Apache 2.0
Download-URL: https://github.com/zlxwl/rasa_print/archive/v0.3.1.tar.gz
Project-URL: Bug Reports, https://github.com/zlxwl/rasa_print/issues
Project-URL: Source, https://github.com/zlxwl/rasa_print
Keywords: nlp machine-learning machine-learning-library bot bots botkit rasa conversational-agents conversational-ai chatbotchatbot-framework bot-framework
Platform: UNKNOWN
Requires-Dist: rasa (~=1.1.3)
Requires-Dist: jieba (~=0.39)
Requires-Dist: bert-serving-client (==1.8.9)
